[
    {"name":"girasole", "categoria":"fiore da giardino", "prezzo":"18", "img":"./media/img-cards-products/Girasole.jpg"},
    {"name":"margherita", "categoria":"fiore da giardino", "prezzo":"10", "img":"./media/img-cards-products/Margherita.jpg"},
    {"name":"papavero", "categoria":"fiore da giardino", "prezzo":"12", "img":"./media/img-cards-products/Papavero.jpg"},
    {"name":"narciso", "categoria":"fiore da giardino", "prezzo":"19", "img":"./media/img-cards-products/Narciso.jpg"},
    {"name":"dalia", "categoria":"fiore da giardino", "prezzo":"21", "img":"./media/img-cards-products/Dalia.jpg"},

    {"name":"orchidea", "categoria":"fiore da casa", "prezzo":"25", "img":"./media/img-cards-products/Orchidea.jpg"},
    {"name":"gardenia", "categoria":"fiore da casa", "prezzo":"23", "img":"./media/img-cards-products/Gardenia.jpg"},
    {"name":"peonia", "categoria":"fiore da casa", "prezzo":"22", "img":"./media/img-cards-products/Peonia.jpg"},
    {"name":"loto", "categoria":"fiore da casa", "prezzo":"30", "img":"./media/img-cards-products/Loto.jpg"},
    {"name":"camelia", "categoria":"fiore da casa", "prezzo":"24", "img":"./media/img-cards-products/Camelia.jpg"},

    {"name":"rosa", "categoria":"fiore da balcone", "prezzo":"20", "img":"./media/img-cards-products/Rosa.jpg"},
    {"name":"tulipano", "categoria":"fiore da balcone", "prezzo":"15", "img":"./media/img-cards-products/Tulipano.jpg"},
    {"name":"lavanda", "categoria":"fiore da balcone", "prezzo":"14", "img":"https://picsum.photos/200?r"},
    {"name":"viola", "categoria":"fiore da balcone", "prezzo":"11", "img":"https://picsum.photos/200?r"},
    {"name":"anemone", "categoria":"fiore da balcone", "prezzo":"16", "img":"https://picsum.photos/200?r"},


    {"name":"aloe vera", "categoria":"pianta medicinale", "prezzo":"18", "img":"https://picsum.photos/200"},
    {"name":"lavanda", "categoria":"pianta medicinale", "prezzo":"14", "img":"https://picsum.photos/200"},
    {"name":"echinacea", "categoria":"pianta medicinale", "prezzo":"20", "img":"https://picsum.photos/200"},
    {"name":"menta", "categoria":"pianta medicinale", "prezzo":"12", "img":"https://picsum.photos/200"},
    {"name":"melissa", "categoria":"pianta medicinale", "prezzo":"13", "img":"https://picsum.photos/200"},

    {"name":"cactus", "categoria":"pianta grassa", "prezzo":"12", "img":"https://picsum.photos/200"},
    {"name":"echeveria", "categoria":"pianta grassa", "prezzo":"14", "img":"https://picsum.photos/200"},
    {"name":"crassula", "categoria":"pianta grassa", "prezzo":"19", "img":"https://picsum.photos/200"},
    {"name":"sedum", "categoria":"pianta grassa", "prezzo":"11", "img":"https://picsum.photos/200"},
    {"name":"agave", "categoria":"pianta grassa", "prezzo":"22", "img":"https://picsum.photos/200"},

    {"name":"rosmarino", "categoria":"pianta aromatica", "prezzo":"10", "img":"https://picsum.photos/200"},
    {"name":"basilico", "categoria":"pianta aromatica", "prezzo":"9", "img":"https://picsum.photos/200"},
    {"name":"salvia", "categoria":"pianta aromatica", "prezzo":"11", "img":"https://picsum.photos/200"},
    {"name":"timo", "categoria":"pianta aromatica", "prezzo":"8", "img":"https://picsum.photos/200"},
    {"name":"origano", "categoria":"pianta aromatica", "prezzo":"10", "img":"https://picsum.photos/200"}
    
  ]
  